MANIFEST.in
README.md
requirements.txt
setup.cfg
setup.py
pygsmmodule/__init__.py
pygsmmodule/__main__.py
pygsmmodule.egg-info/PKG-INFO
pygsmmodule.egg-info/SOURCES.txt
pygsmmodule.egg-info/dependency_links.txt
pygsmmodule.egg-info/not-zip-safe
pygsmmodule.egg-info/requires.txt
pygsmmodule.egg-info/top_level.txt
pygsmmodule/imei/__init__.py
pygsmmodule/imei/imei.py
pygsmmodule/shared/__init__.py
pygsmmodule/shared/support.py
pygsmmodule/shared/typesandconsts.py
pygsmmodule/supplementary/__init__.py
pygsmmodule/supplementary/get_imei.py
pygsmmodule/uart_support/__init__.py
pygsmmodule/uart_support/base_uart.py
pygsmmodule/uart_support/shared.py