Metadata-Version: 1.0
Name: pygsmmodule
Version: 0.1.5.0
Summary: GSM modem control libraty for SIM800/SIM900 modules
Home-page: https://github.com/JFF-Bohdan/pygsmmodule
Author: Bohdan Danishevsky
Author-email: dbn@aminis.com.ua
License: MIT
Keywords: GSM,sim module,SIM-800,SIM 800, SIM-900,SIM 900
Platform: UNKNOWN
